intellicomm/__init__.py
intellicomm/client.py
intellicomm/http_client.py
intellicomm/http_server.py
intellicomm/models.py
intellicomm/payments.py
intellicomm/server.py
intellicomm-0.0.2.dist-info/licenses/LICENSE
intellicomm-0.0.2.dist-info/METADATA
intellicomm-0.0.2.dist-info/WHEEL
intellicomm-0.0.2.dist-info/top_level.txt
intellicomm-0.0.2.dist-info/RECORD
