Metadata-Version: 2.4
Name: intellicomm
Version: 0.0.2
Summary: IntelliComm Protocol (ICP) - Intelligent Communication Framework with x402 payment integration.
Author-email: Ahsen Tahir <ahsentahir007@gmail.com>
License: MIT License
Project-URL: Homepage, https://github.com/AhsenTahir/IntelliComm-Protocol-ICP
Project-URL: Repository, https://github.com/AhsenTahir/IntelliComm-Protocol-ICP
Requires-Python: >=3.9
License-File: LICENSE
Requires-Dist: rich==14.2.0
Requires-Dist: fastapi>=0.109.0
Requires-Dist: uvicorn[standard]>=0.27.0
Requires-Dist: python-multipart>=0.0.6
Requires-Dist: x402>=0.1.0
Requires-Dist: eth-account>=0.11.0
Requires-Dist: httpx>=0.26.0
Requires-Dist: python-dotenv>=1.0.0
Dynamic: license-file
